{
    "inventory": [
      {
        "Price": 1,
        "Quantity": 3,
        "_id": "5b7049b4f8d9d100140f7f93",
        "QR_Code": "37000224006",
        "Name": "Tide Original HE Turbo",
        "Description": "Liquid",
        "Weight": "1.18 litres",
        "Location": "Laundry",
        "__v": 0
      },
      {
        "Price": 1,
        "Quantity": 4,
        "_id": "5b7049b4f8d9d100140f7f94",
        "QR_Code": "28000943516",
        "Name": "Maggi",
        "Description": "8 Piece",
        "Weight": "8oz",
        "Location": "Pantry",
        "__v": 0
      },
      {
        "Price": 1,
        "Quantity": 3,
        "_id": "5b7049b4f8d9d100140f7f95",
        "QR_Code": "44600016283",
        "Name": "Clorox Wipes",
        "Description": "Disinfectant",
        "Weight": "null",
        "Location": "Toiletries",
        "__v": 0
      },
      {
        "Price": 1,
        "Quantity": 1,
        "_id": "5b7049b4f8d9d100140f7f96",
        "QR_Code": "0",
        "Name": "Sujata Aata",
        "Description": "Sujata Whole Weat",
        "Weight": "20 Lbs",
        "Location": "Pantry",
        "__v": 0
      },
      {
        "Price": 1,
        "Quantity": 5,
        "_id": "5b7049b4f8d9d100140f7f97",
        "QR_Code": "16000124790",
        "Name": "Honey Nut Cheerios Cereal",
        "Description": "Cereal Breakfast",
        "Weight": "10.8 Oz",
        "Location": "Pantry",
        "__v": 0
      },
      {
        "Price": 1,
        "Quantity": 0,
        "_id": "5b7049b4f8d9d100140f7f98",
        "QR_Code": "8904147432859",
        "Name": "Cumin Seeds Jeera",
        "Description": "IB",
        "Weight": "28 Oz",
        "Location": "Pantry",
        "__v": 0
      },
      {
        "Price": 1,
        "Quantity": 0,
        "_id": "5b7049b4f8d9d100140f7f99",
        "QR_Code": "820987654175",
        "Name": "Red Rajma Big",
        "Description": "IB Red Kidney Beans",
        "Weight": "2 Lbs",
        "Location": "Pantry",
        "__v": 0
      },
      {
        "Price": 1,
        "Quantity": 1,
        "_id": "5b7049b4f8d9d100140f7f9a",
        "QR_Code": "820987654197",
        "Name": "Moong Dal",
        "Description": "IB",
        "Weight": "4 Lbs",
        "Location": "Pantry",
        "__v": 0
      },
      {
        "Price": 1,
        "Quantity": 1,
        "_id": "5b7049b4f8d9d100140f7f9b",
        "QR_Code": "13131313024",
        "Name": "Chana Dal",
        "Description": "GM",
        "Weight": "4 Lbs",
        "Location": "Pantry",
        "__v": 0
      },
      {
        "Price": 1,
        "Quantity": 1,
        "_id": "5b7049b4f8d9d100140f7f9c",
        "QR_Code": "838927501245",
        "Name": "Khazana Organic Toor Dal",
        "Description": "Costco",
        "Weight": "112 Oz",
        "Location": "Pantry",
        "__v": 0
      },
      {
        "Price": 1,
        "Quantity": 3,
        "_id": "5b7049b4f8d9d100140f7f9d",
        "QR_Code": "6080919333721",
        "Name": "Clover Honey",
        "Description": "Kirkland",
        "Weight": "80 Oz",
        "Location": "Pantry",
        "__v": 0
      },
      {
        "Price": 1,
        "Quantity": 1,
        "_id": "5b7049b4f8d9d100140f7f9e",
        "QR_Code": "85239084335",
        "Name": "Almond Box",
        "Description": "Archer Farms",
        "Weight": "32 Oz",
        "Location": "Pantry",
        "__v": 0
      },
      {
        "Price": 1,
        "Quantity": 1,
        "_id": "5b7049b4f8d9d100140f7f9f",
        "QR_Code": "51179171411",
        "Name": "Idli Rawa",
        "Description": "Swad",
        "Weight": "2 Lb",
        "Location": "Pantry",
        "__v": 0
      },
      {
        "Price": 1,
        "Quantity": 4,
        "_id": "5b7049b4f8d9d100140f7fa0",
        "QR_Code": "50428500170",
        "Name": "Pistachio",
        "Description": "Gold Emblem Unsalted",
        "Weight": "null",
        "Location": "Kitchen",
        "__v": 0
      },
      {
        "Price": 1,
        "Quantity": 1,
        "_id": "5b7049b4f8d9d100140f7fa1",
        "QR_Code": "8901747003670",
        "Name": "Wagh Bakri Tea",
        "Description": "Indian Tea",
        "Weight": "32 Oz",
        "Location": "Kitchen",
        "__v": 0
      },
      {
        "Price": 1,
        "Quantity": 1,
        "_id": "5b7049b4f8d9d100140f7fa2",
        "QR_Code": "8904082780343",
        "Name": "Uttam Idli",
        "Description": "",
        "Weight": "7 Oz",
        "Location": "Kitchen",
        "__v": 0
      },
      {
        "Price": 1,
        "Quantity": 1,
        "_id": "5b7049b4f8d9d100140f7fa3",
        "QR_Code": "8901155102323",
        "Name": "Gits Rice Idli",
        "Description": "",
        "Weight": "17.5 Oz",
        "Location": "Kitchen",
        "__v": 0
      },
      {
        "Price": 1,
        "Quantity": 1,
        "_id": "5b7049b4f8d9d100140f7fa4",
        "QR_Code": "748023300867",
        "Name": "Elbows Macaroni",
        "Description": "Baronia",
        "Weight": "16 Oz",
        "Location": "Kitchen",
        "__v": 0
      },
      {
        "Price": 1,
        "Quantity": 1,
        "_id": "5b7049b4f8d9d100140f7fa5",
        "QR_Code": "8901595851218",
        "Name": "Chings Veg Hakka Noodles",
        "Description": "",
        "Weight": "5.3 Oz",
        "Location": "Kitchen",
        "__v": 0
      },
      {
        "Price": 1,
        "Quantity": 1,
        "_id": "5b7049b4f8d9d100140f7fa6",
        "QR_Code": "820987654464",
        "Name": "Golden Raisins",
        "Description": "IB",
        "Weight": "400 gms",
        "Location": "Kitchen",
        "__v": 0
      },
      {
        "Price": 0,
        "Quantity": 1,
        "_id": "5b71312a8815da0014cfebd3",
        "QR_Code": "0",
        "Name": "Dawn Dishwasher Detergent",
        "Description": "Refill Blue Color",
        "Weight": "1 litre",
        "Location": "Laundry",
        "__v": 0
      },
      {
        "Price": 0,
        "Quantity": 0,
        "_id": "5b71daa2e1b8d4001477bea7",
        "QR_Code": "0",
        "Name": "Dettol",
        "Description": "Big Bottle",
        "Weight": "",
        "Location": "Toiletries",
        "__v": 0
      },
      {
        "Price": 0,
        "Quantity": 2,
        "_id": "5b71db3be1b8d4001477bea8",
        "QR_Code": "381371019410",
        "Name": "Aveeno Baby Daily Moisture Lotion",
        "Description": "Lavender and Vanila",
        "Weight": "18 Oz",
        "Location": "Cosmetics",
        "__v": 0
      },
      {
        "Price": 0,
        "Quantity": 1,
        "_id": "5b71db9be1b8d4001477bea9",
        "QR_Code": "381370038443",
        "Name": "Aveeno Daily Moisturizing Lotion",
        "Description": "",
        "Weight": "18 Oz",
        "Location": "Cosmetics",
        "__v": 0
      },
      {
        "Price": 0,
        "Quantity": 0,
        "_id": "5b71dcd4e1b8d4001477beaa",
        "QR_Code": "0",
        "Name": "Air Wick Automatic Spray",
        "Description": "Refills",
        "Weight": "6 Oz",
        "Location": "Toiletries",
        "__v": 0
      },
      {
        "Price": 12,
        "Quantity": 1,
        "_id": "5b71dd3de1b8d4001477beab",
        "QR_Code": "0",
        "Name": "GRB Ghee",
        "Description": "Cow Ghee",
        "Weight": "900 ml",
        "Location": "Kitchen",
        "__v": 0
      },
      {
        "Price": 0,
        "Quantity": 2,
        "_id": "5b71dd67e1b8d4001477beac",
        "QR_Code": "0",
        "Name": "Coconut Oil",
        "Description": "Cooking Oil",
        "Weight": "",
        "Location": "Kitchen",
        "__v": 0
      },
      {
        "Price": 5,
        "Quantity": 1,
        "_id": "5b71dd7ee1b8d4001477bead",
        "QR_Code": "0",
        "Name": "Mustard Oil",
        "Description": "Dabur",
        "Weight": "900 ml",
        "Location": "Kitchen",
        "__v": 0
      },
      {
        "Price": 0,
        "Quantity": 5,
        "_id": "5b71ddc9e1b8d4001477beae",
        "QR_Code": "0",
        "Name": "Colgate Toothpaste",
        "Description": "Various Flavours",
        "Weight": "6 Oz",
        "Location": "Toiletries",
        "__v": 0
      },
      {
        "Price": 0,
        "Quantity": 10,
        "_id": "5b71dde4e1b8d4001477beaf",
        "QR_Code": "0",
        "Name": "Tooth Brush",
        "Description": "Oral B",
        "Weight": "",
        "Location": "Toiletries",
        "__v": 0
      },
      {
        "Price": 0,
        "Quantity": 1,
        "_id": "5b71df04e1b8d4001477beb1",
        "QR_Code": "51700973309",
        "Name": "Finish Powerball - Dishwashing Tablets",
        "Description": "All in 1-94ct - Dishwasher Detergent",
        "Weight": "94 count",
        "Location": "Laundry",
        "__v": 0
      },
      {
        "Price": 0,
        "Quantity": 1,
        "_id": "5b71de38e1b8d4001477beb0",
        "QR_Code": "0",
        "Name": "Tide PODS 3 in 1 HE Turbo Laundry Detergent Pacs",
        "Description": "Spring Meadow Scent",
        "Weight": "81 count",
        "Location": "Laundry",
        "__v": 0
      },
      {
        "Price": 15,
        "Quantity": 2,
        "_id": "5b71dfc2e1b8d4001477beb2",
        "QR_Code": "37000992691",
        "Name": "Cascade Platinum Dishwasher Pods",
        "Description": "Fresh Scent, 92 Count",
        "Weight": "92 count",
        "Location": "Laundry",
        "__v": 0
      },
      {
        "Price": 12,
        "Quantity": 1,
        "_id": "5b71e056e1b8d4001477beb3",
        "QR_Code": "898999000022",
        "Name": "Vita Coco Water",
        "Description": "18 Bottle Pack",
        "Weight": "11.1 Oz",
        "Location": "Pantry",
        "__v": 0
      },
      {
        "Price": 12,
        "Quantity": 3,
        "_id": "5b71e07de1b8d4001477beb4",
        "QR_Code": "0",
        "Name": "Kirkland Coco Water",
        "Description": "12 Bottle Pack",
        "Weight": "11.1 Oz",
        "Location": "Pantry",
        "__v": 0
      },
      {
        "Price": 0.25,
        "Quantity": 16,
        "_id": "5b71e404e1b8d4001477beb5",
        "QR_Code": "0",
        "Name": "Parle G",
        "Description": "Biscuit",
        "Weight": "2 Oz",
        "Location": "Pantry",
        "__v": 0
      },
      {
        "Price": 0,
        "Quantity": 2,
        "_id": "5b71e427e1b8d4001477beb6",
        "QR_Code": "0",
        "Name": "Marie Gold",
        "Description": "Biscuits",
        "Weight": "5 Oz",
        "Location": "Pantry",
        "__v": 0
      },
      {
        "Price": 9,
        "Quantity": 1,
        "_id": "5b71e452e1b8d4001477beb7",
        "QR_Code": "0",
        "Name": "Rice Parliament",
        "Description": "Ruby Classic Red",
        "Weight": "10 lbs",
        "Location": "Pantry",
        "__v": 0
      },
      {
        "Price": 0,
        "Quantity": 0,
        "_id": "5b71e4b3e1b8d4001477beb8",
        "QR_Code": "0",
        "Name": "Johnsons Baby Powder",
        "Description": "",
        "Weight": "32 Oz",
        "Location": "Toiletries",
        "__v": 0
      },
      {
        "Price": 1.5,
        "Quantity": 0,
        "_id": "5b71ece1e1b8d4001477beb9",
        "QR_Code": "0",
        "Name": "Cut Mango Pickles",
        "Description": "Priya",
        "Weight": "300 gm",
        "Location": "Pantry",
        "__v": 0
      },
      {
        "Price": 0,
        "Quantity": 2,
        "_id": "5b71ed1be1b8d4001477beba",
        "QR_Code": "0",
        "Name": "Salt",
        "Description": "",
        "Weight": "32 Oz",
        "Location": "Pantry",
        "__v": 0
      },
      {
        "Price": 10,
        "Quantity": 1,
        "_id": "5b71ed3be1b8d4001477bebb",
        "QR_Code": "0",
        "Name": "Sugar",
        "Description": "Organic Costco",
        "Weight": "4 Lbs",
        "Location": "Pantry",
        "__v": 0
      },
      {
        "Price": 0,
        "Quantity": 0,
        "_id": "5b71ed4fe1b8d4001477bebc",
        "QR_Code": "0",
        "Name": "Sugar Walmart",
        "Description": "",
        "Weight": "32 Oz",
        "Location": "Pantry",
        "__v": 0
      },
      {
        "Price": 8,
        "Quantity": 1,
        "_id": "5b723d2603febe0014427d01",
        "QR_Code": "381371023905",
        "Name": "Aveeno Baby Wash and Shampoo",
        "Description": "Lightly Scented",
        "Weight": "18 Oz",
        "Location": "Cosmetics",
        "__v": 0
      },
      {
        "Price": 9,
        "Quantity": 1,
        "_id": "5b723d8e03febe0014427d02",
        "QR_Code": "381370012978",
        "Name": "Aveeno Body Wash",
        "Description": "Daily Moisturizing",
        "Weight": "18 Oz",
        "Location": "Toiletries",
        "__v": 0
      },
      {
        "Price": 8,
        "Quantity": 1,
        "_id": "5b723ded03febe0014427d03",
        "QR_Code": "381371168231",
        "Name": "Aveeno Body Yogurt",
        "Description": "Moisturizer",
        "Weight": "7 Oz",
        "Location": "Cosmetics",
        "__v": 0
      },
      {
        "Price": 4,
        "Quantity": 2,
        "_id": "5b723f2f03febe0014427d04",
        "QR_Code": "70501017128",
        "Name": "Neutrogena Face Wash",
        "Description": "Oil Free Acne Wash",
        "Weight": "9 Oz",
        "Location": "Toiletries",
        "__v": 0
      },
      {
        "Price": 2,
        "Quantity": 3,
        "_id": "5b723f6203febe0014427d05",
        "QR_Code": "37000905295",
        "Name": "Old Spice Body Wash",
        "Description": "Timber Flavour",
        "Weight": "16 Oz",
        "Location": "Toiletries",
        "__v": 0
      },
      {
        "Price": 5,
        "Quantity": 2,
        "_id": "5b723fc303febe0014427d06",
        "QR_Code": "74182292669",
        "Name": "Soft soap Refill",
        "Description": "Hand Soap Costco",
        "Weight": "80 Oz",
        "Location": "Toiletries",
        "__v": 0
      },
      {
        "Price": 10,
        "Quantity": 1,
        "_id": "5b72407203febe0014427d07",
        "QR_Code": "0",
        "Name": "Bounty Trash Bags",
        "Description": "Fresh Scent",
        "Weight": "40 Bags",
        "Location": "Laundry",
        "__v": 0
      },
      {
        "Price": 2,
        "Quantity": 5,
        "_id": "5b7240f503febe0014427d08",
        "QR_Code": "36000724448",
        "Name": "Cottonelle Flushable Wet Wipes",
        "Description": "Clean Rippple",
        "Weight": "42 Count",
        "Location": "Toiletries",
        "__v": 0
      },
      {
        "Price": 1,
        "Quantity": 2,
        "_id": "5b7241ea03febe0014427d09",
        "QR_Code": "47400303317",
        "Name": "Gillette Foamy",
        "Description": "Shaving Foam",
        "Weight": "11 Oz",
        "Location": "Toiletries",
        "__v": 0
      },
      {
        "Price": 1,
        "Quantity": 2,
        "_id": "5b72425503febe0014427d0a",
        "QR_Code": "70922104223",
        "Name": "Bowl Fresh",
        "Description": "Blue Color Toilet Color",
        "Weight": "3.4 Oz",
        "Location": "Toiletries",
        "__v": 0
      },
      {
        "Price": 0,
        "Quantity": 1,
        "_id": "5b72d03993668300141f53f5",
        "QR_Code": "36000452570",
        "Name": "Cottonelle Toilet Paper",
        "Description": "Gentle with Aloe E",
        "Weight": "12 Pack",
        "Location": "Toiletries",
        "__v": 0
      },
      {
        "Price": 0,
        "Quantity": 3,
        "_id": "5b72d0f093668300141f53f6",
        "QR_Code": "83689182783",
        "Name": "Plenty Paper Towels",
        "Description": "Ultra Premium Plus",
        "Weight": "6 Rolls",
        "Location": "Toiletries",
        "__v": 0
      },
      {
        "Price": 0,
        "Quantity": 1,
        "_id": "5b72db9283d25900140edff3",
        "QR_Code": "10900060523",
        "Name": "Reynolds Aluminium Foil",
        "Description": "Heavy Duty",
        "Weight": "250 Sq Ft",
        "Location": "Kitchen",
        "__v": 0
      },
      {
        "Price": 0,
        "Quantity": 1,
        "_id": "5b763a0aaf025b0014b58198",
        "QR_Code": "0",
        "Name": "Kala Chana",
        "Description": "",
        "Weight": "",
        "Location": "Pantry",
        "__v": 0
      },
      {
        "Price": 0,
        "Quantity": 0,
        "_id": "5b763ad5af025b0014b58199",
        "QR_Code": "840965002783",
        "Name": "MTR Multigrain Dosa",
        "Description": "",
        "Weight": "17 Oz",
        "Location": "Pantry",
        "__v": 0
      },
      {
        "Price": 0,
        "Quantity": 0,
        "_id": "5b763af7af025b0014b5819a",
        "QR_Code": "840965002837",
        "Name": "MTR Oats Upma",
        "Description": "",
        "Weight": "0",
        "Location": "Pantry",
        "__v": 0
      },
      {
        "Price": 0,
        "Quantity": 0,
        "_id": "5b763b24af025b0014b5819b",
        "QR_Code": "840965002790",
        "Name": "MTR Ragi Rava Idli",
        "Description": "",
        "Weight": "17 Oz",
        "Location": "Pantry",
        "__v": 0
      },
      {
        "Price": 0,
        "Quantity": 0,
        "_id": "5b763b4eaf025b0014b5819c",
        "QR_Code": "840965000260",
        "Name": "MTR Ragi Dosa",
        "Description": "",
        "Weight": "17 Oz",
        "Location": "Pantry",
        "__v": 0
      },
      {
        "Price": 0,
        "Quantity": 5,
        "_id": "5b763ba8af025b0014b5819d",
        "QR_Code": "6291007905877",
        "Name": "Bourbon",
        "Description": "Small Pack",
        "Weight": "100 gm",
        "Location": "Pantry",
        "__v": 0
      },
      {
        "Price": 0,
        "Quantity": 0,
        "_id": "5b763d73af025b0014b5819e",
        "QR_Code": "8906032011019",
        "Name": "Nutrela Soya",
        "Description": "Soya Mini Chunks",
        "Weight": "200g",
        "Location": "Pantry",
        "__v": 0
      },
      {
        "Price": 0,
        "Quantity": 1,
        "_id": "5b76e833d7bb35001474ddca",
        "QR_Code": "51179170209",
        "Name": "Maida",
        "Description": "Swad Brand",
        "Weight": "4 Lbs",
        "Location": "Pantry",
        "__v": 0
      },
      {
        "Price": 0,
        "Quantity": 1,
        "_id": "5b76e8b5d7bb35001474ddcb",
        "QR_Code": "51179241367",
        "Name": "Phool Makhana",
        "Description": "Swad Brand",
        "Weight": "7 Oz",
        "Location": "Pantry",
        "__v": 0
      },
      {
        "Price": 0,
        "Quantity": 2,
        "_id": "5b76eba5d7bb35001474ddcc",
        "QR_Code": "84022200156",
        "Name": "LG Hing",
        "Description": "Asafoetida Powder",
        "Weight": "100 gm",
        "Location": "Pantry",
        "__v": 0
      },
      {
        "Price": 0,
        "Quantity": 1,
        "_id": "5b76f508359008001473daba",
        "QR_Code": "8901571001064",
        "Name": "ENO",
        "Description": "Regular Blue",
        "Weight": "100 gm",
        "Location": "Kitchen",
        "__v": 0
      },
      {
        "Price": 0,
        "Quantity": 1,
        "_id": "5b76f771359008001473dabb",
        "QR_Code": "9661916499",
        "Name": "Black Pepper Powder",
        "Description": "Coarse Ground Kirkland",
        "Weight": "12.7 Oz",
        "Location": "Kitchen",
        "__v": 0
      },
      {
        "Price": 0,
        "Quantity": 1,
        "_id": "5b76f7a6359008001473dabc",
        "QR_Code": "9661965087",
        "Name": "Gound Cinnamon",
        "Description": "Kirkland Powder",
        "Weight": "10.7 Oz",
        "Location": "Kitchen",
        "__v": 0
      },
      {
        "Price": 0,
        "Quantity": 0,
        "_id": "5b76f949359008001473dabd",
        "QR_Code": "9661964950",
        "Name": "Black Pepper Peppercorn",
        "Description": "Kirkland Whole Black",
        "Weight": "14.1 Oz",
        "Location": "Kitchen",
        "__v": 0
      },
      {
        "Price": 0,
        "Quantity": 0,
        "_id": "5b76fa1f359008001473dabe",
        "QR_Code": "8964000122037",
        "Name": "Rooh Afza",
        "Description": "Hamdard",
        "Weight": "800 ml",
        "Location": "Kitchen",
        "__v": 0
      },
      {
        "Price": 0,
        "Quantity": 1,
        "_id": "5b76fa79359008001473dabf",
        "QR_Code": "51179100206",
        "Name": "Black Eye Peas Lobiya",
        "Description": "Swad Brand",
        "Weight": "2 Lbs",
        "Location": "Kitchen",
        "__v": 0
      },
      {
        "Price": 0,
        "Quantity": 0,
        "_id": "5b76fe17359008001473dac0",
        "QR_Code": "8904147410130",
        "Name": "Mustard Seeds Rai",
        "Description": "Adani Spices",
        "Weight": "7 Oz",
        "Location": "Kitchen",
        "__v": 0
      },
      {
        "Price": 1.5,
        "Quantity": 0,
        "_id": "5b79982066b969001482b12b",
        "Name": "Red Chilli Pickle",
        "Description": "In oil with garlic priya",
        "QR_Code": "",
        "Weight": "300 gm",
        "Location": "Kitchen",
        "__v": 0
      },
      {
        "Price": 1.5,
        "Quantity": 0,
        "_id": "5b79984266b969001482b12c",
        "Name": "Green Chilli pickle",
        "Description": "Oil with garlic priya",
        "QR_Code": "",
        "Weight": "300 gm",
        "Location": "Kitchen",
        "__v": 0
      },
      {
        "Price": 1.5,
        "Quantity": 0,
        "_id": "5b79985a66b969001482b12d",
        "Name": "Lime Ginger Pickle",
        "Description": "Without garlic priya",
        "QR_Code": "",
        "Weight": "300 gm",
        "Location": "Kitchen",
        "__v": 0
      },
      {
        "Price": 2.5,
        "Quantity": 0,
        "_id": "5b7a183bebf35a0014d9c4fb",
        "Name": "Oreo Cereal",
        "Description": "Cereal",
        "QR_Code": "",
        "Weight": "",
        "Location": "Pantry",
        "__v": 0
      },
      {
        "Price": 4.55,
        "Quantity": 16,
        "_id": "5b7a4bda0c93f000143ebba0",
        "Name": "Cheetos",
        "Description": "Crunchy",
        "QR_Code": "000000",
        "Weight": "1 Oz",
        "Location": "Pantry",
        "__v": 0
      },
      {
        "Price": 3.49,
        "Quantity": 1,
        "_id": "5b8749c5beaf030014a714f2",
        "Name": "Kala Namak Powder",
        "Description": "Swad",
        "QR_Code": "051179340954",
        "Weight": "14 Oz",
        "Location": "Pantry",
        "__v": 0
      },
      {
        "Price": 0,
        "Quantity": 1,
        "_id": "5b91ef2527b8d80014ddb289",
        "Name": "Charmin  Toilet Paper",
        "Description": "Ultra Soft",
        "QR_Code": "037000163061",
        "Weight": "36 Piece",
        "Location": "Toiletries",
        "__v": 0
      },
      {
        "Price": 0,
        "Quantity": 1,
        "_id": "5b9342158f42f4001459d604",
        "Name": "Shan Garam Masala",
        "Description": "Zafrani Garam Masala",
        "QR_Code": "788821060099",
        "Weight": "100gm",
        "Location": "Kitchen",
        "__v": 0
      },
      {
        "Price": 0,
        "Quantity": 1,
        "_id": "5b956380688ca00014ffc262",
        "Name": "Febreze scent spray",
        "Description": "",
        "QR_Code": "",
        "Weight": "8.8 Oz",
        "Location": "Laundry",
        "__v": 0
      },
      {
        "Price": 0,
        "Quantity": 2,
        "_id": "5b956457688ca00014ffc264",
        "Name": "Kirkland Canola Oil",
        "Description": "",
        "QR_Code": "027000690611",
        "Weight": "1 Galon",
        "Location": "Kitchen",
        "__v": 0
      },
      {
        "Price": 0,
        "Quantity": 1,
        "_id": "5b956490688ca00014ffc265",
        "Name": "Organic Chia Seeds",
        "Description": "Prince and Spring",
        "QR_Code": "81314021763",
        "Weight": "2 Lbs",
        "Location": "Kitchen",
        "__v": 0
      },
      {
        "Price": 0,
        "Quantity": 1,
        "_id": "5b95669f688ca00014ffc266",
        "Name": "Aveeno pure renewal shampoo",
        "Description": "Sulfate free green",
        "QR_Code": "381371150595",
        "Weight": "10.5 oz",
        "Location": "Toiletries",
        "__v": 0
      },
      {
        "Price": 0,
        "Quantity": 1,
        "_id": "5b9566dd688ca00014ffc267",
        "Name": "Listerene Green",
        "Description": "",
        "QR_Code": "312547428255",
        "Weight": "500 ml",
        "Location": "Toiletries",
        "__v": 0
      },
      {
        "Price": 0,
        "Quantity": 1,
        "_id": "5b956720688ca00014ffc268",
        "Name": "Toilet Cleaning Gel",
        "Description": "Glade Bubbles",
        "QR_Code": "025700713814",
        "Weight": "1.34 Oz",
        "Location": "Toiletries",
        "__v": 0
      },
      {
        "Price": 0,
        "Quantity": 0,
        "_id": "5b9c79c5b31a1b00149f56f8",
        "Name": "Swad Besan",
        "Description": "",
        "QR_Code": "",
        "Weight": "",
        "Location": "Pantry",
        "__v": 0
      },
      {
        "Price": 0,
        "Quantity": 1,
        "_id": "5b9d50b491525e0014454c59",
        "Name": "Red Chilli Powder",
        "Description": "",
        "QR_Code": "",
        "Weight": "",
        "Location": "Kitchen",
        "__v": 0
      },
      {
        "Price": 0,
        "Quantity": 0,
        "_id": "5ba06e406d03da0014699696",
        "Name": "Soya Sauce",
        "Description": "Chings",
        "QR_Code": "",
        "Weight": "",
        "Location": "Kitchen",
        "__v": 0
      },
      {
        "Price": 0,
        "Quantity": 0,
        "_id": "5ba06e5e6d03da0014699697",
        "Name": "Red Schezwan Sauce",
        "Description": "Chings",
        "QR_Code": "",
        "Weight": "",
        "Location": "Kitchen",
        "__v": 0
      },
      {
        "Price": 0,
        "Quantity": 1,
        "_id": "5ba074316d03da0014699698",
        "Name": "Poha",
        "Description": "",
        "QR_Code": "",
        "Weight": "",
        "Location": "Kitchen",
        "__v": 0
      },
      {
        "Price": 0,
        "Quantity": 1,
        "_id": "5ba074416d03da0014699699",
        "Name": "Vatna Matar",
        "Description": "",
        "QR_Code": "",
        "Weight": "",
        "Location": "Kitchen",
        "__v": 0
      }
    ],
    "responseCode": 200,
    "message": "Greetings from KD Home Inventory"
  }